img2scad/__init__.py
img2scad/img2scad.py
img2scad-0.5.dist-info/LICENSE.txt
img2scad-0.5.dist-info/METADATA
img2scad-0.5.dist-info/WHEEL
img2scad-0.5.dist-info/entry_points.txt
img2scad-0.5.dist-info/top_level.txt
img2scad-0.5.dist-info/RECORD
