Metadata-Version: 2.1
Name: img2scad
Version: 0.5
Summary: Image to OpenSCAD converter
Home-page: https://gitlab.com/engmark/img2scad
Download-URL: https://gitlab.com/engmark/img2scad
Author: Victor Engmark
Author-email: victor@engmark.name
Maintainer: Victor Engmark
Maintainer-email: victor@engmark.name
License: GPL v3 or newer
Keywords: image images height heightmap heightmaps elevation convert converter OpenSCAD SCAD
Platform: POSIX
Platform: Windows
Classifier: Development Status :: 3 - Alpha
Classifier: Environment :: Console
Classifier: Intended Audience :: End Users/Desktop
Classifier: License :: OSI Approved :: GNU General Public License (GPL)
Classifier: Operating System :: OS Independent
Classifier: Programming Language :: Python :: 3
Classifier: Topic :: Artistic Software
Classifier: Topic :: Multimedia :: Graphics :: 3D Modeling
Classifier: Topic :: Multimedia :: Graphics :: Graphics Conversion
License-File: LICENSE.txt
Requires-Dist: Pillow (==9.4.0)
